project_generator_definitions/__init__.py
project_generator_definitions/create_command.py
project_generator_definitions/definitions.py
project_generator_definitions/main.py
project_generator_definitions/tools.py
project_generator_definitions/mcu/ambiq/ama3b1kk-kbr.yaml
project_generator_definitions/mcu/arm/cortex-m0.yaml
project_generator_definitions/mcu/arm/cortex-m0plus.yaml
project_generator_definitions/mcu/arm/cortex-m23.yaml
project_generator_definitions/mcu/arm/cortex-m3.yaml
project_generator_definitions/mcu/arm/cortex-m33.yaml
project_generator_definitions/mcu/arm/cortex-m4-fpu.yaml
project_generator_definitions/mcu/arm/cortex-m4.yaml
project_generator_definitions/mcu/arm/cortex-m7.yaml
project_generator_definitions/mcu/arm-ssg/beetle.yaml
project_generator_definitions/mcu/atmel/atsam3u2c.yaml
project_generator_definitions/mcu/atmel/samd21g18a.yaml
project_generator_definitions/mcu/atmel/samd21j18a.yaml
project_generator_definitions/mcu/atmel/samr21g18a.yaml
project_generator_definitions/mcu/atmel/samr21j18a.yaml
project_generator_definitions/mcu/cypress/psoc5lp.yaml
project_generator_definitions/mcu/freescale/mk20dx128xxx5.yaml
project_generator_definitions/mcu/freescale/mk20dx256xxx7.yaml
project_generator_definitions/mcu/freescale/mk22dn512xxx5.yaml
project_generator_definitions/mcu/freescale/mk22fn128xxx10.yaml
project_generator_definitions/mcu/freescale/mk64fn1m0xxx12.yaml
project_generator_definitions/mcu/freescale/mkl05z32xxx4.yaml
project_generator_definitions/mcu/freescale/mkl25z128xxx4.yaml
project_generator_definitions/mcu/freescale/mkl26z128xxx4.yaml
project_generator_definitions/mcu/freescale/mkl27z256xxx4.yaml
project_generator_definitions/mcu/freescale/mkl43z256xxx4.yaml
project_generator_definitions/mcu/freescale/mkl46z256xxx4.yaml
project_generator_definitions/mcu/gigadevice/gd32f303xe.yaml
project_generator_definitions/mcu/maxim/max32600x85.yaml
project_generator_definitions/mcu/maxim/max32620.yaml
project_generator_definitions-0.2.46.dist-info/LICENSE
project_generator_definitions-0.2.46.dist-info/METADATA
project_generator_definitions-0.2.46.dist-info/WHEEL
project_generator_definitions-0.2.46.dist-info/entry_points.txt
project_generator_definitions-0.2.46.dist-info/top_level.txt
project_generator_definitions-0.2.46.dist-info/RECORD
